[
  {
    "meeting_date": "2026-07-29",
    "label": "Jul 29, 2026",
    "current_target_range": "3.50-3.75",
    "fetched_at": "2026-07-14T17:20:44Z",
    "probabilities": [
      {
        "rate": "3.50-3.75",
        "probability": 0.834
      },
      {
        "rate": "3.75-4.00",
        "probability": 0.166
      }
    ]
  },
  {
    "meeting_date": "2026-09-16",
    "label": "Sep 16, 2026",
    "current_target_range": "3.50-3.75",
    "fetched_at": "2026-07-14T17:20:44Z",
    "probabilities": [
      {
        "rate": "3.50-3.75",
        "probability": 0.377
      },
      {
        "rate": "3.75-4.00",
        "probability": 0.532
      },
      {
        "rate": "4.00-4.25",
        "probability": 0.091
      }
    ]
  },
  {
    "meeting_date": "2026-10-28",
    "label": "Oct 28, 2026",
    "current_target_range": "3.50-3.75",
    "fetched_at": "2026-07-14T17:20:44Z",
    "probabilities": [
      {
        "rate": "3.50-3.75",
        "probability": 0.282
      },
      {
        "rate": "3.75-4.00",
        "probability": 0.493
      },
      {
        "rate": "4.00-4.25",
        "probability": 0.202
      },
      {
        "rate": "4.25-4.50",
        "probability": 0.023
      }
    ]
  },
  {
    "meeting_date": "2026-12-09",
    "label": "Dec 09, 2026",
    "current_target_range": "3.50-3.75",
    "fetched_at": "2026-07-14T17:20:44Z",
    "probabilities": [
      {
        "rate": "3.50-3.75",
        "probability": 0.178
      },
      {
        "rate": "3.75-4.00",
        "probability": 0.415
      },
      {
        "rate": "4.00-4.25",
        "probability": 0.309
      },
      {
        "rate": "4.25-4.50",
        "probability": 0.089
      },
      {
        "rate": "4.50-4.75",
        "probability": 0.008
      }
    ]
  },
  {
    "meeting_date": "2027-01-27",
    "label": "Jan 27, 2027",
    "current_target_range": "3.50-3.75",
    "fetched_at": "2026-07-14T17:20:44Z",
    "probabilities": [
      {
        "rate": "3.50-3.75",
        "probability": 0.144
      },
      {
        "rate": "3.75-4.00",
        "probability": 0.37
      },
      {
        "rate": "4.00-4.25",
        "probability": 0.33
      },
      {
        "rate": "4.25-4.50",
        "probability": 0.131
      },
      {
        "rate": "4.50-4.75",
        "probability": 0.024
      },
      {
        "rate": "4.75-5.00",
        "probability": 0.002
      }
    ]
  }
]